sqlalchemy_utilities/__init__.py
sqlalchemy_utilities/serilizers.py
sqlalchemy_utilities-1.0.5.dist-info/METADATA
sqlalchemy_utilities-1.0.5.dist-info/WHEEL
sqlalchemy_utilities-1.0.5.dist-info/top_level.txt
sqlalchemy_utilities-1.0.5.dist-info/RECORD
